old_norwegian_dictionary/__init__.py
old_norwegian_dictionary/dictionary.py
old_norwegian_dictionary/reader.py
old_norwegian_dictionary/resources/__init__.py
old_norwegian_dictionary/resources/dictionary.json
old_norwegian_dictionary-0.9.0.dist-info/LICENSE
old_norwegian_dictionary-0.9.0.dist-info/METADATA
old_norwegian_dictionary-0.9.0.dist-info/WHEEL
old_norwegian_dictionary-0.9.0.dist-info/top_level.txt
old_norwegian_dictionary-0.9.0.dist-info/RECORD
