Metadata-Version: 2.1
Name: old-norwegian-dictionary
Version: 0.9.0
Summary: Old Norwegian/Norse Dictionary for Python. From 'Dictionary of the Old Norwegian Language'
Home-page: https://github.com/stscoundrel/old-norwegian-dictionary-py
Author: stscoundrel
License: UNKNOWN
Platform: UNKNOWN
Requires-Python: >=3.9
License-File: LICENSE
